markkk/__init__.py
markkk/color.py
markkk/encoding.py
markkk/file.py
markkk/logger.py
markkk/time.py
markkk-0.0.16.dist-info/LICENSE
markkk-0.0.16.dist-info/METADATA
markkk-0.0.16.dist-info/WHEEL
markkk-0.0.16.dist-info/top_level.txt
markkk-0.0.16.dist-info/RECORD
