Metadata-Version: 2.1
Name: markkk
Version: 0.0.16
Summary: Python convenient utilities for personal usage
Home-page: https://github.com/MarkHershey/markkk
Author: Mark Huang
Author-email: mark.h.huang@gmail.com
License: UNKNOWN
Platform: UNKNOWN
Classifier: Development Status :: 3 - Alpha
Classifier: Topic :: Utilities
Classifier: Intended Audience :: Developers
Classifier: Programming Language :: Python :: 3
Classifier: Programming Language :: Python :: 3.6
Classifier: Programming Language :: Python :: 3.7
Classifier: Programming Language :: Python :: 3.8
Classifier: License :: OSI Approved :: MIT License
Classifier: Operating System :: OS Independent
Classifier: Natural Language :: English
Classifier: Framework :: tox
Classifier: Framework :: Pytest
Requires-Python: >=3.6
Requires-Dist: colorlog (>=4.1.0)
Provides-Extra: dev
Requires-Dist: pytest ; extra == 'dev'
Requires-Dist: tox ; extra == 'dev'
Requires-Dist: wheel ; extra == 'dev'
